nwb4fp/__init__.py
nwb4fp/analyses/__init__.py
nwb4fp/analyses/border_scores.py
nwb4fp/analyses/bordercells.py
nwb4fp/analyses/data.py
nwb4fp/analyses/fields.py
nwb4fp/analyses/functional_scores.py
nwb4fp/analyses/gridcells.py
nwb4fp/analyses/maps.py
nwb4fp/analyses/stats.py
nwb4fp/analyses/tools.py
nwb4fp/analyses/examples/tracking_plot.py
nwb4fp/analyses/phase_precession/__init__.py
nwb4fp/analyses/phase_precession/core.py
nwb4fp/analyses/phase_precession/corr_cc.py
nwb4fp/analyses/phase_precession/tests/test_core.py
nwb4fp/analyses/tests/test_bordercells.py
nwb4fp/analyses/tests/test_fields.py
nwb4fp/analyses/tests/test_gridcells.py
nwb4fp/analyses/tests/test_maps.py
nwb4fp/analyses/tests/test_stats.py
nwb4fp/data/__init__.py
nwb4fp/data/append_property2nwb.py
nwb4fp/data/helpers.py
nwb4fp/main/__init__.py
nwb4fp/main/main_create_nwb.py
nwb4fp/postprocess/Get_positions.py
nwb4fp/postprocess/__init__.py
nwb4fp/postprocess/add_wfcor.py
nwb4fp/postprocess/dlc_kinematic.py
nwb4fp/postprocess/extract_wf.py
nwb4fp/postprocess/get_potential_merge.py
nwb4fp/postprocess/lfp_channel.py
nwb4fp/postprocess/nwbPHYnOPHYS.py
nwb4fp/postprocess/quality_metrix.py
nwb4fp/postprocess/analysis/phase_precession/__init__.py
nwb4fp/postprocess/analysis/tSC/__init__.py
nwb4fp/preprocess/__init__.py
nwb4fp/preprocess/copy_file.py
nwb4fp/preprocess/down_sample.py
nwb4fp/preprocess/down_sample_lfp.py
nwb4fp/preprocess/extract_lfp.py
nwb4fp/preprocess/get_path.py
nwb4fp/preprocess/load_data.py
nwb4fp/preprocess/run_phy.py
nwb4fp/spatial-maps/__init__.py
nwb4fp/spatial-maps/setup.py
nwb4fp/spatial-maps/build/lib/spatial_maps/__init__.py
nwb4fp/spatial-maps/build/lib/spatial_maps/bordercells.py
nwb4fp/spatial-maps/build/lib/spatial_maps/fields.py
nwb4fp/spatial-maps/build/lib/spatial_maps/gridcells.py
nwb4fp/spatial-maps/build/lib/spatial_maps/maps.py
nwb4fp/spatial-maps/build/lib/spatial_maps/stats.py
nwb4fp/spatial-maps/build/lib/spatial_maps/tools.py
nwb4fp-0.8.0.4.dist-info/LICENSE
nwb4fp-0.8.0.4.dist-info/METADATA
nwb4fp-0.8.0.4.dist-info/WHEEL
nwb4fp-0.8.0.4.dist-info/top_level.txt
nwb4fp-0.8.0.4.dist-info/RECORD
