Metadata-Version: 2.1
Name: nwb4fp
Version: 0.8.0.4
Summary: Description of my package
Home-page: https://github.com/sachuriga/QuattrocoloLab-nwb4fp
Author: sachuriga
Author-email: sachuriga.sachuriga@ntnu.no
License-File: LICENSE
Requires-Dist: aiobotocore ==2.11.2
Requires-Dist: aiohttp ==3.9.3
Requires-Dist: aioitertools ==0.11.0
Requires-Dist: aiosignal ==1.3.1
Requires-Dist: anyio ==4.3.0
Requires-Dist: argon2-cffi ==23.1.0
Requires-Dist: argon2-cffi-bindings ==21.2.0
Requires-Dist: arrow ==1.3.0
Requires-Dist: asciitree ==0.3.3
Requires-Dist: asttokens ==2.4.1
Requires-Dist: async-lru ==2.0.4
Requires-Dist: attrs ==23.2.0
Requires-Dist: Babel ==2.14.0
Requires-Dist: beautifulsoup4 ==4.12.3
Requires-Dist: bleach ==6.1.0
Requires-Dist: blosc2 ==2.5.1
Requires-Dist: botocore ==1.34.34
Requires-Dist: certifi ==2024.2.2
Requires-Dist: cffi ==1.16.0
Requires-Dist: charset-normalizer ==3.3.2
Requires-Dist: click ==8.1.7
Requires-Dist: colorama ==0.4.6
Requires-Dist: comm ==0.2.1
Requires-Dist: debugpy ==1.8.1
Requires-Dist: decorator ==5.1.1
Requires-Dist: defusedxml ==0.7.1
Requires-Dist: docutils ==0.20.1
Requires-Dist: entrypoints ==0.4
Requires-Dist: executing ==2.0.1
Requires-Dist: fasteners ==0.19
Requires-Dist: fastjsonschema ==2.19.1
Requires-Dist: fqdn ==1.5.1
Requires-Dist: frozenlist ==1.4.1
Requires-Dist: fsspec ==2024.2.0
Requires-Dist: h11 ==0.14.0
Requires-Dist: h5py ==3.10.0
Requires-Dist: hdmf ==3.12.2
Requires-Dist: hdmf-zarr ==0.5.0
Requires-Dist: httpcore ==1.0.4
Requires-Dist: httpx ==0.27.0
Requires-Dist: idna ==3.6
Requires-Dist: importlib-metadata ==7.0.1
Requires-Dist: ipykernel ==6.29.3
Requires-Dist: ipython ==8.22.1
Requires-Dist: isodate ==0.6.1
Requires-Dist: isoduration ==20.11.0
Requires-Dist: jaraco.classes ==3.3.1
Requires-Dist: jedi ==0.19.1
Requires-Dist: Jinja2 ==3.1.3
Requires-Dist: jmespath ==1.0.1
Requires-Dist: joblib ==1.3.2
Requires-Dist: json5 ==0.9.18
Requires-Dist: jsonpointer ==2.4
Requires-Dist: jsonschema ==4.21.1
Requires-Dist: jsonschema-specifications ==2023.12.1
Requires-Dist: jupyter-client ==8.6.0
Requires-Dist: jupyter-core ==5.7.1
Requires-Dist: jupyter-events ==0.9.0
Requires-Dist: jupyter-lsp ==2.2.3
Requires-Dist: jupyter-server ==2.12.5
Requires-Dist: jupyter-server-terminals ==0.5.2
Requires-Dist: jupyterlab ==4.1.2
Requires-Dist: jupyterlab-pygments ==0.3.0
Requires-Dist: jupyterlab-server ==2.25.3
Requires-Dist: keyring ==24.3.0
Requires-Dist: llvmlite ==0.42.0
Requires-Dist: markdown-it-py ==3.0.0
Requires-Dist: MarkupSafe ==2.1.5
Requires-Dist: matplotlib-inline ==0.1.6
Requires-Dist: matplotlib ==3.8.4
Requires-Dist: mdurl ==0.1.2
Requires-Dist: mistune ==3.0.2
Requires-Dist: more-itertools ==10.2.0
Requires-Dist: msgpack ==1.0.8
Requires-Dist: multidict ==6.0.5
Requires-Dist: natsort ==8.4.0
Requires-Dist: nbclient ==0.9.0
Requires-Dist: nbconvert ==7.16.1
Requires-Dist: nbformat ==5.9.2
Requires-Dist: ndindex ==1.8
Requires-Dist: neo ==0.13.0
Requires-Dist: nest-asyncio ==1.6.0
Requires-Dist: neuroconv ==0.4.8
Requires-Dist: nh3 ==0.2.15
Requires-Dist: notebook ==7.1.1
Requires-Dist: notebook-shim ==0.2.4
Requires-Dist: numba ==0.59.0
Requires-Dist: numcodecs ==0.11.0
Requires-Dist: numexpr ==2.9.0
Requires-Dist: numpy ==1.26.4
Requires-Dist: nwbinspector ==0.4.33
Requires-Dist: overrides ==7.7.0
Requires-Dist: packaging ==21.3
Requires-Dist: pandas ==2.2.1
Requires-Dist: pandocfilters ==1.5.1
Requires-Dist: parse ==1.20.1
Requires-Dist: parso ==0.8.3
Requires-Dist: pkginfo ==1.9.6
Requires-Dist: platformdirs ==4.2.0
Requires-Dist: probeinterface ==0.2.21
Requires-Dist: prometheus-client ==0.20.0
Requires-Dist: prompt-toolkit ==3.0.43
Requires-Dist: psutil ==5.9.8
Requires-Dist: pure-eval ==0.2.2
Requires-Dist: py-cpuinfo ==9.0.0
Requires-Dist: pycparser ==2.21
Requires-Dist: Pygments ==2.17.2
Requires-Dist: pynwb ==2.6.0
Requires-Dist: pyopenephys ==1.2.0
Requires-Dist: pyparsing ==3.1.1
Requires-Dist: python-dateutil ==2.8.2
Requires-Dist: python-json-logger ==2.0.7
Requires-Dist: pytz ==2024.1
Requires-Dist: pywin32 ==306
Requires-Dist: pywin32-ctypes ==0.2.2
Requires-Dist: pywinpty ==2.0.13
Requires-Dist: PyYAML ==6.0.1
Requires-Dist: pyzmq ==25.1.2
Requires-Dist: quantities ==0.15.0
Requires-Dist: readme-renderer ==43.0
Requires-Dist: referencing ==0.33.0
Requires-Dist: requests ==2.31.0
Requires-Dist: requests-toolbelt ==1.0.0
Requires-Dist: rfc3339-validator ==0.1.4
Requires-Dist: rfc3986 ==2.0.0
Requires-Dist: rfc3986-validator ==0.1.1
Requires-Dist: rich ==13.7.0
Requires-Dist: rpds-py ==0.18.0
Requires-Dist: ruamel.yaml ==0.18.6
Requires-Dist: ruamel.yaml.clib ==0.2.8
Requires-Dist: s3fs ==2024.2.0
Requires-Dist: scikit-learn ==1.4.1.post1
Requires-Dist: scipy ==1.12.0
Requires-Dist: Send2Trash ==1.8.2
Requires-Dist: setuptools ==68.2.2
Requires-Dist: six ==1.16.0
Requires-Dist: sniffio ==1.3.1
Requires-Dist: soupsieve ==2.5
Requires-Dist: stack-data ==0.6.3
Requires-Dist: tables ==3.9.2
Requires-Dist: terminado ==0.18.0
Requires-Dist: threadpoolctl ==3.3.0
Requires-Dist: tinycss2 ==1.2.1
Requires-Dist: tornado ==6.4
Requires-Dist: tqdm ==4.66.2
Requires-Dist: traitlets ==5.14.1
Requires-Dist: twine ==5.0.0
Requires-Dist: types-python-dateutil ==2.8.19.20240106
Requires-Dist: typing-extensions ==4.10.0
Requires-Dist: tzdata ==2024.1
Requires-Dist: uri-template ==1.3.0
Requires-Dist: urllib3 ==2.0.7
Requires-Dist: wcwidth ==0.2.13
Requires-Dist: webcolors ==1.13
Requires-Dist: webencodings ==0.5.1
Requires-Dist: websocket-client ==1.7.0
Requires-Dist: wheel ==0.41.2
Requires-Dist: wrapt ==1.16.0
Requires-Dist: xmltodict ==0.13.0
Requires-Dist: yarl ==1.9.4
Requires-Dist: zarr ==2.17.0
Requires-Dist: zipp ==3.17.0
